<?xml version="1.0" encoding="UTF-8" standalone="yes"?>
<metadata>
  <idinfo>
    <citation>
      <citeinfo>
        <origin>Please refer to Dataset Point of Contact.</origin>
        <pubdate/>
        <title>Line-point Intercept Data</title>
        <geoform>tabular digital data</geoform>
        <onlink>www.landscapedatacommons.org</onlink>
        <lworkcit>
          <citeinfo>
            <origin>Please refer to Dataset Point of Contact.</origin>
            <pubdate/>
            <title>Please refer to the Projects table in the Landscape Data Commons database.</title>
            <geoform>tabular digital data</geoform>
          </citeinfo>
        </lworkcit>
      </citeinfo>
    </citation>
    <descript>
      <abstract>The Line-point intercept method measures the proportion of the soil surface that is covered by different species of vascular plants, as well as rocks, litter, mosses and lichens. Total cover is the proportion of the soil surface that is covered by vascular plant parts, litter, rocks larger than 5 mm in diameter, mosses and lichens. Total cover is positively correlated with soil and site stability and hydrologic function. It protects the soil surface from raindrop impact, thereby limiting detachment of soil particles and physical crusting of the soil surface. Additionally, higher cover generally means there are more obstructions to water flow. Reference(s): Herrick, J.E., J. Van Zee, S.E. McCord, J.W. Karl, E. Courtright, and L. Burkett. 2018. The Monitoring Manual for Grassland, Shrubland, and Savanna Ecosystems. USDA-ARS.</abstract>
      <purpose>Line-point intercept provides data that can be used to calculate plant cover and composition indicators, including the percentage bare ground, foliar and basal cover by species and plant functional or structural groups.</purpose>
    </descript>
    <timeperd>
      <timeinfo>
        <rngdates>
          <begdate/>
          <enddate/>
        </rngdates>
      </timeinfo>
      <current>observed</current>
    </timeperd>
    <status>
      <progress>In work</progress>
      <update>Continually</update>
    </status>
    <spdom>
      <bounding>
        <westbc/>
        <eastbc/>
        <northbc/>
        <southbc/>
      </bounding>
    </spdom>
    <keywords>
      <theme>
        <themekt>ISO 19115 Topic Category</themekt>
        <themekey>geoscientificInformation</themekey>
        <themekey>climatologyMeteorologyAtmosphere</themekey>
        <themekey>environment</themekey>
      </theme>
      <theme>
        <themekt>LPI data</themekt>
        <themekey>LPI</themekey>
        <themekey>line point</themekey>
        <themekey>intercept</themekey>
        <themekey>cover</themekey>
        <themekey>composition</themekey>
      </theme>
    </keywords>
    <accconst>Please refer to the Projects table in the Landscape Data Commons database.</accconst>
    <useconst>Please refer to the Projects table in the Landscape Data Commons database.</useconst>
    <ptcontac>
      <cntinfo>
        <cntperp>
          <cntper>Sarah McCord</cntper>
          <cntorg>Jornada Experimental Range</cntorg>
        </cntperp>
        <cntpos>Research Ecologist</cntpos>
        <cntaddr>
          <addrtype>mailing and physical</addrtype>
          <address>P.O.Box 30003, MSC 3 JER, NMSU</address>
          <city>Las Cruces</city>
          <state>NM</state>
          <postal>88003</postal>
          <country>US</country>
        </cntaddr>
        <cntvoice>575 636 7527</cntvoice>
        <cntemail>sarah.mccord@usda.gov</cntemail>
      </cntinfo>
    </ptcontac>
    <datacred>Please reference "Data Use Agreements" located in the Projects table.</datacred>
  </idinfo>
  <dataqual>
    <attracc>
      <attraccr>Please refer to the Dataset Point of Contact.</attraccr>
    </attracc>
    <logic>Please refer to the Dataset Point of Contact.</logic>
    <complete/>
    <lineage>
      <procstep>
        <procdesc>Data gathered into a harmonized "tall" format using the terradactyl R package gather_lpi() function. https://github.com/Landscape-Data-Commons/terradactyl.</procdesc>
        <procdate/>
      </procstep>
    </lineage>
  </dataqual>
  <spdoinfo>
    <direct>Vector</direct>
    <ptvctinf>
      <sdtsterm>
        <sdtstype>Entity point</sdtstype>
        <ptvctcnt>3</ptvctcnt>
      </sdtsterm>
    </ptvctinf>
  </spdoinfo>
  <eainfo>
    <detailed>
      <enttyp>
        <enttypl>dataLPI</enttypl>
        <enttypd/>
        <enttypds>Producer Defined</enttypds>
        <attr>
          <attrlabl>rid</attrlabl>
          <attrdef/>
          <attrdefs>Producer Defined</attrdefs>
          <attrdomv>
            <udom/>
          </attrdomv>
        </attr>
        <attr>
          <attrlabl>PrimaryKey</attrlabl>
          <attrdef>Unique identifier for each plot-visit.</attrdef>
          <attrdefs>Producer Defined</attrdefs>
          <attrdomv>
            <udom/>
          </attrdomv>
        </attr>
        <attr>
          <attrlabl>DBKey</attrlabl>
          <attrdef>Code denoting original database information about the project.</attrdef>
          <attrdefs>Producer Defined</attrdefs>
          <attrdomv>
            <udom/>
          </attrdomv>
        </attr>
        <attr>
          <attrlabl>ProjectKey</attrlabl>
          <attrdef>Unique identifier of the broader project under which data were collected.</attrdef>
          <attrdefs>Producer Defined</attrdefs>
          <attrdomv>
            <udom/>
          </attrdomv>
        </attr>
        <attr>
          <attrlabl>LineKey</attrlabl>
          <attrdef>Unique key for transect (line).</attrdef>
          <attrdefs>Producer Defined</attrdefs>
          <attrdomv>
            <udom/>
          </attrdomv>
        </attr>
        <attr>
          <attrlabl>RecKey</attrlabl>
          <attrdef>Unique key for Line-point Intercept data collection.</attrdef>
          <attrdefs>Producer Defined</attrdefs>
          <attrdomv>
            <udom/>
          </attrdomv>
        </attr>
        <attr>
          <attrlabl>layer</attrlabl>
          <attrdef>Layer in pin drop (TopCanopy, Lower1, Lower2, ""¦.SoilSurface).</attrdef>
          <attrdefs>Producer Defined</attrdefs>
          <attrdomv>
            <udom/>
          </attrdomv>
        </attr>
        <attr>
          <attrlabl>code</attrlabl>
          <attrdef>Species code, litter code, or surface code recorded by observer.</attrdef>
          <attrdefs>Producer Defined</attrdefs>
          <attrdomv>
            <udom/>
          </attrdomv>
        </attr>
        <attr>
          <attrlabl>chckbox</attrlabl>
          <attrdef>Checkbox designation (1 = true; 0 = false).</attrdef>
          <attrdefs>Producer Defined</attrdefs>
          <attrdomv>
            <udom/>
          </attrdomv>
        </attr>
        <attr>
          <attrlabl>ShrubShape</attrlabl>
          <attrdef>Shrub shape (C = columnar; S = spreading).</attrdef>
          <attrdefs>Producer Defined</attrdefs>
          <attrdomv>
            <udom/>
          </attrdomv>
        </attr>
        <attr>
          <attrlabl>FormType</attrlabl>
          <attrdef>Form for Line-point Intercept data collection.</attrdef>
          <attrdefs>Producer Defined</attrdefs>
          <attrdomv>
            <udom/>
          </attrdomv>
        </attr>
        <attr>
          <attrlabl>FormDate</attrlabl>
          <attrdef>Date data were collected (defaults to today's date although user can modify).</attrdef>
          <attrdefs>Producer Defined</attrdefs>
          <attrdomv>
            <udom/>
          </attrdomv>
        </attr>
        <attr>
          <attrlabl>Direction</attrlabl>
          <attrdef>Denotes whether transect is read from low-to-high (e.g., 0-100 m) or high-to-low (e.g., 100-0 m).</attrdef>
          <attrdefs>Producer Defined</attrdefs>
          <attrdomv>
            <udom/>
          </attrdomv>
        </attr>
        <attr>
          <attrlabl>Measure</attrlabl>
          <attrdef>Data collected in metric. Data originally collected in imperial units are converted to metric.</attrdef>
          <attrdefs>Producer Defined</attrdefs>
          <attrdomv>
            <udom/>
          </attrdomv>
        </attr>
        <attr>
          <attrlabl>LineLengthAmount</attrlabl>
          <attrdef>Length of the Line-point Intercept transect (line).</attrdef>
          <attrdefs>Producer Defined</attrdefs>
          <attrdomv>
            <udom/>
          </attrdomv>
        </attr>
        <attr>
          <attrlabl>SpacingIntervalAmount</attrlabl>
          <attrdef>Length between collection points.</attrdef>
          <attrdefs>Producer Defined</attrdefs>
          <attrdomv>
            <udom/>
          </attrdomv>
        </attr>
        <attr>
          <attrlabl>SpacingType</attrlabl>
          <attrdef>Units for length between collection points (cm, m, ft).</attrdef>
          <attrdefs>Producer Defined</attrdefs>
          <attrdomv>
            <udom/>
          </attrdomv>
        </attr>
        <attr>
          <attrlabl>ShowCheckbox</attrlabl>
          <attrdef>Display checkbox or not (1 = true; 0 = false).</attrdef>
          <attrdefs>Producer Defined</attrdefs>
          <attrdomv>
            <udom/>
          </attrdomv>
        </attr>
        <attr>
          <attrlabl>CheckboxLabel</attrlabl>
          <attrdef>User entered ""label"" for checkbox (e.g., standing dead).</attrdef>
          <attrdefs>Producer Defined</attrdefs>
          <attrdomv>
            <udom/>
          </attrdomv>
        </attr>
        <attr>
          <attrlabl>PointLoc</attrlabl>
          <attrdef>Point location on tape (e.g., 0.5 m)</attrdef>
          <attrdefs>Producer Defined</attrdefs>
          <attrdomv>
            <udom/>
          </attrdomv>
        </attr>
        <attr>
          <attrlabl>PointNbr</attrlabl>
          <attrdef>Point number in sequence on transect (e.g., 1, 2, 3""¦.).</attrdef>
          <attrdefs>Producer Defined</attrdefs>
          <attrdomv>
            <udom/>
          </attrdomv>
        </attr>
        <attr>
          <attrlabl>source</attrlabl>
          <attrdef>Source data format. Required for use of terradactyl</attrdef>
          <attrdefs>Producer Defined</attrdefs>
          <attrdomv>
            <udom/>
          </attrdomv>
        </attr>
        <attr>
          <attrlabl>DateLoadedInDb</attrlabl>
          <attrdef>Date that the data were uploaded into Landscape Data Commons (YYYY-MM-DD).</attrdef>
          <attrdefs>Producer Defined</attrdefs>
          <attrdomv>
            <udom/>
          </attrdomv>
        </attr>
      </enttyp>
    </detailed>
  </eainfo>
  <distinfo>
    <distrib>
      <cntinfo>
        <cntperp>
          <cntper>Sarah McCord</cntper>
          <cntorg>Jornada Experimental Range</cntorg>
        </cntperp>
        <cntpos>Computational Biologist</cntpos>
        <cntaddr>
          <addrtype>mailing and physical</addrtype>
          <address>P.O. Box 30003, MSC 3JER, NMSU</address>
          <city>Las Cruces</city>
          <state>NM</state>
          <postal>88003</postal>
          <country>United States</country>
        </cntaddr>
        <cntvoice>575 636 7527</cntvoice>
        <cntemail>sarah.mccord@usda.gov</cntemail>
      </cntinfo>
    </distrib>
    <distliab>The Landscape Data Commons is freely available for use by the public. The USDA Agricultural Research Service (ARS) and the U.S. Government have not placed any restriction on its use or reproduction of its contents. Although all reasonable efforts have been taken to ensure the accuracy and reliability of the software and data, the ARS and the U.S. Government do not and cannot warrant the performance or results that may be obtained by their use. The ARS and the U.S. Government disclaim all warranties, expressed or implied, including warranties of performance, merchantability or fitness for any particular purpose.</distliab>
    <stdorder>
      <digform>
        <digtinfo>
          <formname>Digital Data</formname>
        </digtinfo>
        <digtopt>
          <onlinopt>
            <computer>
              <networka>
                <networkr>www.landscapedatacommons.org</networkr>
              </networka>
            </computer>
          </onlinopt>
        </digtopt>
      </digform>
      <fees>None</fees>
    </stdorder>
  </distinfo>
  <metainfo>
    <metd/>
    <metc>
      <cntinfo>
        <cntperp>
          <cntper>Sarah McCord</cntper>
          <cntorg>Jornada Experimental Range</cntorg>
        </cntperp>
        <cntpos>Research Ecologist</cntpos>
        <cntaddr>
          <addrtype>mailing and physical</addrtype>
          <address>P.O.Box 30003, MSC 3 JER, NMSU</address>
          <city>Las Cruces</city>
          <state>NM</state>
          <postal>88003</postal>
          <country>US</country>
        </cntaddr>
        <cntvoice>575 636 7527</cntvoice>
        <cntemail>sarah.mccord@usda.gov</cntemail>
      </cntinfo>
    </metc>
    <metstdn>FGDC Content Standard for Digital Geospatial Metadata</metstdn>
    <metstdv>FGDC-STD-001-1998</metstdv>
  </metainfo>
</metadata>